landaupy/__init__.py
landaupy/landau.py
landaupy/langauss.py
landaupy-0.1.dist-info/LICENSE
landaupy-0.1.dist-info/METADATA
landaupy-0.1.dist-info/WHEEL
landaupy-0.1.dist-info/top_level.txt
landaupy-0.1.dist-info/RECORD
