Metadata-Version: 2.1
Name: landaupy
Version: 0.1
Summary: A pure python implementation of the Landau distribution
Home-page: https://github.com/SengerM/landaupy
Author: Matias Senger
Author-email: matias.senger@cern.ch
License: MIT
Platform: UNKNOWN
Classifier: Programming Language :: Python :: 3
Classifier: License :: OSI Approved :: MIT License
Classifier: Operating System :: OS Independent
License-File: LICENSE
Requires-Dist: numpy
